skloess/__init__.py
skloess/_version.py
skloess/skloess.py
skloess/tests/__init__.py
skloess/tests/test_LOESS.py
skloess/tests/test_common.py
skloess-0.1.3.dist-info/METADATA
skloess-0.1.3.dist-info/WHEEL
skloess-0.1.3.dist-info/top_level.txt
skloess-0.1.3.dist-info/RECORD
