Metadata-Version: 2.2
Name: skloess
Version: 0.1.3
Summary: Sklearn compatible implementation of the Locally Estimated Scatterplot Smoothing (LOESS) algorithm
Requires-Python: >=3.12
Requires-Dist: matplotlib>=3.10.0
Requires-Dist: numpy>=2.2.1
Requires-Dist: pytest>=8.3.4
Requires-Dist: scikit-learn>=1.6.1
